vmdpy/__init__.py
vmdpy/vmdpy.py
vmdpy-0.1.dist-info/LICENSE.txt
vmdpy-0.1.dist-info/METADATA
vmdpy-0.1.dist-info/WHEEL
vmdpy-0.1.dist-info/top_level.txt
vmdpy-0.1.dist-info/RECORD
