Metadata-Version: 2.1
Name: vmdpy
Version: 0.1
Summary: Variational Mode Decomposition (VMD) algorithm
Home-page: http://github.com/vrcarva/vmdpy
Author: Vinicius Rezende Carvalho
Author-email: vrcarva@ufmg.br
License: UNKNOWN
Keywords: VMD,variational,decomposition
Platform: UNKNOWN
Classifier: Development Status :: 3 - Alpha
Classifier: Intended Audience :: Science/Research
Classifier: Topic :: Scientific/Engineering :: Mathematics
Classifier: License :: OSI Approved :: MIT License
Classifier: Programming Language :: Python :: 3
Requires-Dist: numpy
